git_system_follower/__init__.py
git_system_follower/cli.py
git_system_follower/develop/__init__.py
git_system_follower/develop/api/__init__.py
git_system_follower/develop/api/cicd_variables.py
git_system_follower/develop/api/templates.py
git_system_follower/develop/api/types.py
git_system_follower/download.py
git_system_follower/errors.py
git_system_follower/git_api/__init__.py
git_system_follower/git_api/git_api.py
git_system_follower/git_api/gitlab_api.py
git_system_follower/git_api/utils.py
git_system_follower/install.py
git_system_follower/logger.py
git_system_follower/package/__init__.py
git_system_follower/package/cicd_variables.py
git_system_follower/package/default.py
git_system_follower/package/deleter.py
git_system_follower/package/initer.py
git_system_follower/package/package_info.py
git_system_follower/package/rollbacker.py
git_system_follower/package/script.py
git_system_follower/package/system.py
git_system_follower/package/templates.py
git_system_follower/package/updater.py
git_system_follower/plugins/__init__.py
git_system_follower/plugins/cli/__init__.py
git_system_follower/plugins/cli/packages/__init__.py
git_system_follower/plugins/cli/packages/default.py
git_system_follower/plugins/cli/packages/manager.py
git_system_follower/plugins/cli/packages/specs.py
git_system_follower/plugins/managers.py
git_system_follower/states.py
git_system_follower/typings/__init__.py
git_system_follower/typings/cli.py
git_system_follower/typings/package.py
git_system_follower/typings/registry.py
git_system_follower/typings/repository.py
git_system_follower/typings/script.py
git_system_follower/uninstall.py
git_system_follower/utils/__init__.py
git_system_follower/utils/cli.py
git_system_follower/utils/logger.py
git_system_follower/utils/output.py
git_system_follower/utils/retry.py
git_system_follower/utils/tmpdir.py
git_system_follower/utils/versions.py
git_system_follower/variables.py
qubership_git_system_follower-0.6.4.dist-info/LICENSE
qubership_git_system_follower-0.6.4.dist-info/METADATA
qubership_git_system_follower-0.6.4.dist-info/WHEEL
qubership_git_system_follower-0.6.4.dist-info/entry_points.txt
qubership_git_system_follower-0.6.4.dist-info/RECORD
