Metadata-Version: 2.3
Name: qubership-git-system-follower
Version: 0.6.4
Summary: The package manager for Git providers
License: Apache-2.0
Author: Qubership
Requires-Python: >=3.10,<4.0
Classifier: License :: OSI Approved :: Apache Software License
Classifier: Programming Language :: Python :: 3
Classifier: Programming Language :: Python :: 3.10
Classifier: Programming Language :: Python :: 3.11
Classifier: Programming Language :: Python :: 3.12
Classifier: Programming Language :: Python :: 3.13
Requires-Dist: click (==8.1.7)
Requires-Dist: cookiecutter (==2.6.0)
Requires-Dist: gitpython (==3.1.43)
Requires-Dist: oras (==0.2.24)
Requires-Dist: outlify (==0.7.0)
Requires-Dist: packaging (==24.1)
Requires-Dist: pluggy (==1.5.0)
Requires-Dist: python-gitlab (>=4.9.0,<5.0.0)
Requires-Dist: pyyaml (==6.0.2)
Requires-Dist: requests (==2.32.3)
